beltosbml
