Metadata-Version: 2.1
Name: beltosbml
Version: 0.0.6
Summary: Package to extend a SBML model with BEL queries
Home-page: https://github.com/VitaminBrad/BELtoSBML
Author: Bradley Wililam English
Author-email: brad.w.english@gmail.com
License: UNKNOWN
Platform: UNKNOWN
Classifier: Programming Language :: Python :: 3
Classifier: License :: OSI Approved :: MIT License
Classifier: Operating System :: OS Independent
Requires-Python: >=3.6
